[
  {
    "id": "occ_120505",
    "sci": "Crotalus_morulus",
    "ts": null,
    "lat": 25.23962,
    "lon": -100.41276,
    "source": "VenomMaps",
    "photo": false,
    "verified": false,
    "source_kind": "other",
    "highlight": false
  },
  {
    "id": "occ_136805",
    "sci": "Crotalus_morulus",
    "ts": null,
    "lat": 24.51972,
    "lon": -99.86962,
    "source": "HUMAN_OBSERVATION",
    "photo": false,
    "verified": true,
    "source_kind": "human_observation",
    "highlight": false
  },
  {
    "id": "occ_137887",
    "sci": "Crotalus_morulus",
    "ts": null,
    "lat": 25.56327,
    "lon": -100.30586,
    "source": "HUMAN_OBSERVATION",
    "photo": false,
    "verified": true,
    "source_kind": "human_observation",
    "highlight": false
  },
  {
    "id": "occ_149262",
    "sci": "Crotalus_morulus",
    "ts": null,
    "lat": 25.30903,
    "lon": -100.13676,
    "source": "HUMAN_OBSERVATION",
    "photo": false,
    "verified": true,
    "source_kind": "human_observation",
    "highlight": false
  },
  {
    "id": "occ_150386",
    "sci": "Crotalus_morulus",
    "ts": null,
    "lat": 24.66727,
    "lon": -100.03177,
    "source": "HUMAN_OBSERVATION",
    "photo": false,
    "verified": true,
    "source_kind": "human_observation",
    "highlight": false
  },
  {
    "id": "occ_156245",
    "sci": "Crotalus_morulus",
    "ts": null,
    "lat": 25.44022,
    "lon": -100.52223,
    "source": "HUMAN_OBSERVATION",
    "photo": false,
    "verified": true,
    "source_kind": "human_observation",
    "highlight": false
  },
  {
    "id": "occ_159108",
    "sci": "Crotalus_morulus",
    "ts": null,
    "lat": 25.67166,
    "lon": -100.75839,
    "source": "HUMAN_OBSERVATION",
    "photo": false,
    "verified": true,
    "source_kind": "human_observation",
    "highlight": false
  },
  {
    "id": "occ_174258",
    "sci": "Crotalus_morulus",
    "ts": null,
    "lat": 25.27695,
    "lon": -100.23364,
    "source": "HUMAN_OBSERVATION",
    "photo": false,
    "verified": true,
    "source_kind": "human_observation",
    "highlight": false
  },
  {
    "id": "occ_210360",
    "sci": "Crotalus_morulus",
    "ts": null,
    "lat": 25.31158,
    "lon": -100.2525,
    "source": "HUMAN_OBSERVATION",
    "photo": false,
    "verified": true,
    "source_kind": "human_observation",
    "highlight": false
  },
  {
    "id": "occ_222112",
    "sci": "Crotalus_morulus",
    "ts": null,
    "lat": 25.36901,
    "lon": -100.4902,
    "source": "HUMAN_OBSERVATION",
    "photo": false,
    "verified": true,
    "source_kind": "human_observation",
    "highlight": false
  },
  {
    "id": "occ_223803",
    "sci": "Crotalus_morulus",
    "ts": null,
    "lat": 25.61742,
    "lon": -100.23814,
    "source": "HUMAN_OBSERVATION",
    "photo": false,
    "verified": true,
    "source_kind": "human_observation",
    "highlight": false
  },
  {
    "id": "occ_235640",
    "sci": "Crotalus_morulus",
    "ts": null,
    "lat": 25.62005,
    "lon": -100.41447,
    "source": "HUMAN_OBSERVATION",
    "photo": false,
    "verified": true,
    "source_kind": "human_observation",
    "highlight": false
  },
  {
    "id": "occ_238349",
    "sci": "Crotalus_morulus",
    "ts": null,
    "lat": 24.50627,
    "lon": -99.8764,
    "source": "HUMAN_OBSERVATION",
    "photo": false,
    "verified": true,
    "source_kind": "human_observation",
    "highlight": false
  },
  {
    "id": "occ_238354",
    "sci": "Crotalus_morulus",
    "ts": null,
    "lat": 24.51853,
    "lon": -99.8865,
    "source": "HUMAN_OBSERVATION",
    "photo": false,
    "verified": true,
    "source_kind": "human_observation",
    "highlight": false
  },
  {
    "id": "occ_238356",
    "sci": "Crotalus_morulus",
    "ts": null,
    "lat": 24.51056,
    "lon": -99.86843,
    "source": "HUMAN_OBSERVATION",
    "photo": false,
    "verified": true,
    "source_kind": "human_observation",
    "highlight": false
  },
  {
    "id": "occ_244287",
    "sci": "Crotalus_morulus",
    "ts": null,
    "lat": 24.56713,
    "lon": -99.98616,
    "source": "HUMAN_OBSERVATION",
    "photo": false,
    "verified": true,
    "source_kind": "human_observation",
    "highlight": false
  },
  {
    "id": "occ_244291",
    "sci": "Crotalus_morulus",
    "ts": null,
    "lat": 24.5277,
    "lon": -100.11724,
    "source": "HUMAN_OBSERVATION",
    "photo": false,
    "verified": true,
    "source_kind": "human_observation",
    "highlight": false
  },
  {
    "id": "occ_245501",
    "sci": "Crotalus_morulus",
    "ts": null,
    "lat": 25.31029,
    "lon": -100.5756,
    "source": "HUMAN_OBSERVATION",
    "photo": false,
    "verified": true,
    "source_kind": "human_observation",
    "highlight": false
  },
  {
    "id": "occ_249532",
    "sci": "Crotalus_morulus",
    "ts": null,
    "lat": 25.29003,
    "lon": -100.54258,
    "source": "HUMAN_OBSERVATION",
    "photo": false,
    "verified": true,
    "source_kind": "human_observation",
    "highlight": false
  },
  {
    "id": "occ_299526",
    "sci": "Crotalus_morulus",
    "ts": null,
    "lat": 25.35218,
    "lon": -100.92558,
    "source": "NA",
    "photo": false,
    "verified": false,
    "source_kind": "other",
    "highlight": false
  },
  {
    "id": "occ_299527",
    "sci": "Crotalus_morulus",
    "ts": null,
    "lat": 25.37677,
    "lon": -100.91058,
    "source": "NA",
    "photo": false,
    "verified": false,
    "source_kind": "other",
    "highlight": false
  },
  {
    "id": "occ_299528",
    "sci": "Crotalus_morulus",
    "ts": null,
    "lat": 25.20724,
    "lon": -100.90729,
    "source": "NA",
    "photo": false,
    "verified": false,
    "source_kind": "other",
    "highlight": false
  },
  {
    "id": "occ_299529",
    "sci": "Crotalus_morulus",
    "ts": null,
    "lat": 25.36712,
    "lon": -100.83045,
    "source": "NA",
    "photo": false,
    "verified": false,
    "source_kind": "other",
    "highlight": false
  },
  {
    "id": "occ_299530",
    "sci": "Crotalus_morulus",
    "ts": null,
    "lat": 25.60461,
    "lon": -100.58386,
    "source": "NA",
    "photo": false,
    "verified": false,
    "source_kind": "other",
    "highlight": false
  },
  {
    "id": "occ_299531",
    "sci": "Crotalus_morulus",
    "ts": null,
    "lat": 25.86034,
    "lon": -100.53016,
    "source": "NA",
    "photo": false,
    "verified": false,
    "source_kind": "other",
    "highlight": false
  },
  {
    "id": "occ_299532",
    "sci": "Crotalus_morulus",
    "ts": null,
    "lat": 25.65,
    "lon": -100.458,
    "source": "NA",
    "photo": false,
    "verified": false,
    "source_kind": "other",
    "highlight": false
  },
  {
    "id": "occ_299533",
    "sci": "Crotalus_morulus",
    "ts": null,
    "lat": 25.65,
    "lon": -100.45778,
    "source": "NA",
    "photo": false,
    "verified": false,
    "source_kind": "other",
    "highlight": false
  },
  {
    "id": "occ_299534",
    "sci": "Crotalus_morulus",
    "ts": null,
    "lat": 25.26803,
    "lon": -100.4113,
    "source": "NA",
    "photo": false,
    "verified": false,
    "source_kind": "other",
    "highlight": false
  },
  {
    "id": "occ_299535",
    "sci": "Crotalus_morulus",
    "ts": null,
    "lat": 25.60361,
    "lon": -100.39833,
    "source": "NA",
    "photo": false,
    "verified": false,
    "source_kind": "other",
    "highlight": false
  },
  {
    "id": "occ_299537",
    "sci": "Crotalus_morulus",
    "ts": null,
    "lat": 25.604,
    "lon": -100.398,
    "source": "NA",
    "photo": false,
    "verified": false,
    "source_kind": "other",
    "highlight": false
  },
  {
    "id": "occ_299539",
    "sci": "Crotalus_morulus",
    "ts": null,
    "lat": 25.71028,
    "lon": -100.37306,
    "source": "NA",
    "photo": false,
    "verified": false,
    "source_kind": "other",
    "highlight": false
  },
  {
    "id": "occ_299540",
    "sci": "Crotalus_morulus",
    "ts": null,
    "lat": 25.71,
    "lon": -100.373,
    "source": "NA",
    "photo": false,
    "verified": false,
    "source_kind": "other",
    "highlight": false
  },
  {
    "id": "occ_299541",
    "sci": "Crotalus_morulus",
    "ts": null,
    "lat": 25.58722,
    "lon": -100.36917,
    "source": "NA",
    "photo": false,
    "verified": false,
    "source_kind": "other",
    "highlight": false
  },
  {
    "id": "occ_299542",
    "sci": "Crotalus_morulus",
    "ts": null,
    "lat": 25.587,
    "lon": -100.369,
    "source": "NA",
    "photo": false,
    "verified": false,
    "source_kind": "other",
    "highlight": false
  },
  {
    "id": "occ_299543",
    "sci": "Crotalus_morulus",
    "ts": null,
    "lat": 24.98597,
    "lon": -100.26149,
    "source": "NA",
    "photo": false,
    "verified": false,
    "source_kind": "other",
    "highlight": false
  },
  {
    "id": "occ_299547",
    "sci": "Crotalus_morulus",
    "ts": null,
    "lat": 24.95472,
    "lon": -100.26133,
    "source": "NA",
    "photo": false,
    "verified": false,
    "source_kind": "other",
    "highlight": false
  },
  {
    "id": "occ_299550",
    "sci": "Crotalus_morulus",
    "ts": null,
    "lat": 24.87611,
    "lon": -100.22028,
    "source": "NA",
    "photo": false,
    "verified": false,
    "source_kind": "other",
    "highlight": false
  },
  {
    "id": "occ_299557",
    "sci": "Crotalus_morulus",
    "ts": null,
    "lat": 24.876,
    "lon": -100.22,
    "source": "NA",
    "photo": false,
    "verified": false,
    "source_kind": "other",
    "highlight": false
  },
  {
    "id": "occ_299564",
    "sci": "Crotalus_morulus",
    "ts": null,
    "lat": 25.29778,
    "lon": -100.1625,
    "source": "NA",
    "photo": false,
    "verified": false,
    "source_kind": "other",
    "highlight": false
  },
  {
    "id": "occ_299565",
    "sci": "Crotalus_morulus",
    "ts": null,
    "lat": 25.298,
    "lon": -100.162,
    "source": "NA",
    "photo": false,
    "verified": false,
    "source_kind": "other",
    "highlight": false
  },
  {
    "id": "occ_299566",
    "sci": "Crotalus_morulus",
    "ts": null,
    "lat": 25.35,
    "lon": -100.16,
    "source": "NA",
    "photo": false,
    "verified": false,
    "source_kind": "other",
    "highlight": false
  },
  {
    "id": "occ_299568",
    "sci": "Crotalus_morulus",
    "ts": null,
    "lat": 24.83276,
    "lon": -100.13919,
    "source": "NA",
    "photo": false,
    "verified": false,
    "source_kind": "other",
    "highlight": false
  },
  {
    "id": "occ_299569",
    "sci": "Crotalus_morulus",
    "ts": null,
    "lat": 24.825,
    "lon": -100.09167,
    "source": "NA",
    "photo": false,
    "verified": false,
    "source_kind": "other",
    "highlight": false
  },
  {
    "id": "occ_299570",
    "sci": "Crotalus_morulus",
    "ts": null,
    "lat": 24.82732,
    "lon": -100.07654,
    "source": "NA",
    "photo": false,
    "verified": false,
    "source_kind": "other",
    "highlight": false
  },
  {
    "id": "occ_299577",
    "sci": "Crotalus_morulus",
    "ts": null,
    "lat": 24.82694,
    "lon": -100.07639,
    "source": "NA",
    "photo": false,
    "verified": false,
    "source_kind": "other",
    "highlight": false
  },
  {
    "id": "occ_299585",
    "sci": "Crotalus_morulus",
    "ts": null,
    "lat": 24.827,
    "lon": -100.076,
    "source": "NA",
    "photo": false,
    "verified": false,
    "source_kind": "other",
    "highlight": false
  },
  {
    "id": "occ_299593",
    "sci": "Crotalus_morulus",
    "ts": null,
    "lat": 24.70444,
    "lon": -100.03,
    "source": "NA",
    "photo": false,
    "verified": false,
    "source_kind": "other",
    "highlight": false
  },
  {
    "id": "occ_299594",
    "sci": "Crotalus_morulus",
    "ts": null,
    "lat": 24.704,
    "lon": -100.03,
    "source": "NA",
    "photo": false,
    "verified": false,
    "source_kind": "other",
    "highlight": false
  },
  {
    "id": "occ_299595",
    "sci": "Crotalus_morulus",
    "ts": null,
    "lat": 24.592,
    "lon": -99.995,
    "source": "NA",
    "photo": false,
    "verified": false,
    "source_kind": "other",
    "highlight": false
  },
  {
    "id": "occ_299596",
    "sci": "Crotalus_morulus",
    "ts": null,
    "lat": 24.59194,
    "lon": -99.995,
    "source": "NA",
    "photo": false,
    "verified": false,
    "source_kind": "other",
    "highlight": false
  }
]